{
  "tasks": [
    {
      "id": "b241",
      "title": "karam",
      "description": "Author",
      "column": "in progress"
    },
    {
      "id": "171a",
      "title": "Karam1",
      "description": "Autho",
      "column": "in progress"
    },
    {
      "id": "fcd1",
      "title": "Karam",
      "description": "Author4",
      "column": "backlog"
    },
    {
      "id": "a6a0",
      "title": "Karam",
      "description": "Karam2",
      "column": "backlog"
    },
    {
      "id": "d38e",
      "title": "Karam",
      "description": "Author",
      "column": "review"
    },
    {
      "id": "4abb",
      "title": "Karam1",
      "description": "Author",
      "column": "done"
    }
  ]
}